{
    "sections": {
        
        "Aerospace Engineering": {
            "featured": false,
            "config": {
                "num_columns": 1,
                "match": false,
                "show_section_title": true
            },
            "content": [
                [
                    [
                        "header", null, [
                            ["round_icon", "./img/nyuadspace.png", null],
                            ["title", "nyuad.space", null]
                        ]
                    ],
                    [
                        "footer", null, [
                            [
                                "embedded_link", 
                                "https://nyuad-space.github.io/", 
                                [
                                    ["link_text", "Check out the website", null]
                                ]
                            ]
                        ]
                    ]
                ]
            ]
        },
        "nyuad.space projects": {
            "featured": false,
            "config": {
                "num_columns": 2,
                "match": true,
                "show_section_title": false
            },
            "content": [
                [
                    [
                        "header", null, [
                            ["borderless_small_icon", "./img/haloship.png", null],
                            ["title", "Haloship", null],
                            ["subtitle", "Spaceport America Cup 2023", null],
                            ["date", "Aug 2022 - Jun 2023", null]
                        ]
                    ],
                    [
                        "body", null, [
                            ["paragraph", "Haloship is a rocket comprised entirely of mechanical sub-assemblies, allowing for packing into a suitcase, and is equipped with custom flight avionics, encompassing a flight computer and a high-speed data acquisition payload.", null],
                            ["bullets", null, [
                                ["item", "Designed and developed the mechanical subassemblies of a rocket.", null],
                                ["item", "Performed flight and Finite Element Method (FEM) simulations.", null],
                                ["item", "Prepared and finalized detailed GD&T-compliant technical drawings for external manufacturing", null],
                                ["item", "Successfully launched the rocket at the SA Cup 2023 in Las Cruces, New Mexico", null]
                            ]
                        ]
                        ]
                    ],
                    [
                        "footer", null, [
                            [
                                "embedded_link", 
                                "https://nyuad-space.github.io/projects/haloship/", 
                                [
                                    ["link_text", "More Info", null]
                                ]
                            ]
                        ]
                    ]
                ],
                [
                    [
                        "header", null, [
                            ["borderless_small_icon", "./img/hdrm.png", null],
                            ["title", "Hold Down Release Mechanism ", null],
                            ["subtitle", "NASA Jet Propulsion Lab University Crowdsourcing Initiative", null],
                            ["date", "Aug 2022 - Jun 2023", null]
                        ]
                    ],
                    [
                        "body", null, [
                            ["paragraph", "Design project in collaboration between the nyuad.space aerospace team with NASA JPL mentors at Caltech as part of the JPL University Crowdsourcing Initiative (JUCI)", null],
                            ["bullets", null, [
                                ["item", "Reduced system cost from $10,000 to $1000, while maintaining compliance with NASA flight readiness metrics.", null],
                                ["item", "Conducted Finite Element Method (FEM) analysis to evaluate and validate the mechanism’s structural integrity.", null],
                                ["item", "Finalized multiple options of GD&T-compliant technical drawings according to manufacturing method.", null],
                                ["item", "Presented our design to engineers at Caltech JPL in Los Angeles, California.", null]
                            ]
                        ]
                        ]
                    ],
                    [
                        "footer", null, [
                            [
                                "embedded_link", 
                                "https://nyuad-space.github.io/projects/hdrm/", 
                                [
                                    ["link_text", "More Info", null]
                                ]
                            ]
                        ]
                    ]
                ]
            ]
        },
        "Software Engineering": {
            "featured": false,
            "config": {
                "num_columns": 3,
                "match": true,
                "show_section_title": true
            },
            "content": [
                [
                    [
                        "header", null, [
                            ["title", "Portfolio Pier", null],
                            ["date", "Mar 2024 - April 2024", null]
                        ]
                    ],
                    [
                        "body", null, [
                            ["paragraph", "Applied Internet Technologies term project. Portfolio Pier is a platform to host your own portfolio website with custom themes, webpages, and content. Users can register and login to pick their websites theme, desired webpages, and content. Once a portfolio site is created, it becomes visible for the public. Users can easily update their own pages in a process as simple as creating a social media post.", null]
                        ]
                    ],
                    [
                        "footer", null, [
                            [
                                "embedded_link", 
                                "/content.html?project=portfolio-pier", 
                                [
                                    ["link_text", "More Info", null]
                                ]
                            ]
                        ]
                    ]
                ],
                [
                    [
                        "header", null, [
                            ["title", "FizzbuzzDraw", null],
                            ["date", "Apr 2024", null]
                        ]
                    ],
                    [
                        "body", null, [
                            ["paragraph", "One of the Software Engineering assigned projects", null]
                        ]
                    ],
                    [
                        "footer", null, [
                            [
                                "embedded_link", 
                                "https://github.com/software-students-spring2024/5-final-project-spring-2024-team-fizzbuzz-final?tab=readme-ov-file", 
                                [
                                    ["link_text", "Github Repo", null]
                                ]
                            ]
                        ]
                    ]
                ],
                [
                    [
                        "header", null, [
                            ["title", "Ma Tahtahu Khat", null],
                            ["date", "Mar 2024 - April 2024", null]
                        ]
                    ],
                    [
                        "body", null, [
                            ["paragraph", "Natural Language Processing course term project aimed to create a toolchain to perform I’rab, or the Arabic grammatical process of extended sequence tagging.", null]                        ]
                    ],
                    [
                        "footer", null, [
                            [
                                "embedded_link", 
                                "https://github.com/DoodyShark/Ma-Tahtahu-Khat", 
                                [
                                    ["link_text", "Github Repo", null]
                                ]
                            ]
                        ]
                    ]
                ]
            ]
        },
        "More Projects": {
            "featured": false,
            "config": {
                "num_columns": 1,
                "match": true,
                "show_section_title": true

            },
            "content": [
                [
                    [
                        "body", null, [
                            [
                                "paragraph",
                                "To Be Updated...",
                                null
                            ]
                        ]
                    ]
                ]
            ]  
        }
    }
}